{
  "features": [
    {
      "geometry": {
        "coordinates": [
          114.109497,
          22.396428
        ],
        "type": "Point"
      },
      "properties": {
        "marker-size": "small",
        "marker-color": "#ff0f00",
        "providers": "Rackspace",
        "location": "Hong Kong"
      },
      "type": "Feature"
    }
  ],
  "type": "FeatureCollection"
}
